jmdx/__init__.py
jmdx/_version.py
jmdx/space.py
jmdx-0.0.1.dist-info/METADATA
jmdx-0.0.1.dist-info/WHEEL
jmdx-0.0.1.dist-info/top_level.txt
jmdx-0.0.1.dist-info/RECORD
