Metadata-Version: 2.4
Name: jmdx
Version: 0.0.1
Summary: Jax Molecular Dynamics eXtended
Home-page: https://github.com/minu928/jase
Author: minu928
Author-email: minu928@snu.ac.kr
Keywords: jax,molecular dynamics,dft
Requires-Python: >=3.10
Dynamic: author
Dynamic: author-email
Dynamic: home-page
Dynamic: keywords
Dynamic: requires-python
Dynamic: summary
